[
    {
        "record_id": 1,
        "type": "Film",
        "title": "Reverse-engineered heuristic productivity",
        "year": "2000",
        "genre": "tragedia",
        "views": 0
    },
    {
        "record_id": 2,
        "type": "Serial",
        "title": "Open-architected disintermediate collaboration",
        "year": "2010",
        "genre": "horror",
        "views": 0,
        "episode_number": 1,
        "season_number": 1
    },
    {
        "record_id": 3,
        "type": "Serial",
        "title": "Open-architected disintermediate collaboration",
        "year": "2010",
        "genre": "horror",
        "views": 37,
        "episode_number": 2,
        "season_number": 1
    },
    {
        "record_id": 4,
        "type": "Serial",
        "title": "Open-architected disintermediate collaboration",
        "year": "2010",
        "genre": "horror",
        "views": 0,
        "episode_number": 3,
        "season_number": 1
    },
    {
        "record_id": 5,
        "type": "Serial",
        "title": "Open-architected disintermediate collaboration",
        "year": "2010",
        "genre": "horror",
        "views": 0,
        "episode_number": 4,
        "season_number": 1
    },
    {
        "record_id": 6,
        "type": "Serial",
        "title": "Open-architected disintermediate collaboration",
        "year": "2010",
        "genre": "horror",
        "views": 0,
        "episode_number": 5,
        "season_number": 1
    },
    {
        "record_id": 7,
        "type": "Serial",
        "title": "Open-architected disintermediate collaboration",
        "year": "2010",
        "genre": "horror",
        "views": 12,
        "episode_number": 6,
        "season_number": 1
    },
    {
        "record_id": 8,
        "type": "Serial",
        "title": "Open-architected disintermediate collaboration",
        "year": "2010",
        "genre": "horror",
        "views": 0,
        "episode_number": 7,
        "season_number": 1
    },
    {
        "record_id": 9,
        "type": "Serial",
        "title": "Open-architected disintermediate collaboration",
        "year": "2010",
        "genre": "horror",
        "views": 0,
        "episode_number": 8,
        "season_number": 1
    },
    {
        "record_id": 10,
        "type": "Serial",
        "title": "Open-architected disintermediate collaboration",
        "year": "2010",
        "genre": "horror",
        "views": 0,
        "episode_number": 9,
        "season_number": 1
    },
    {
        "record_id": 11,
        "type": "Serial",
        "title": "Open-architected disintermediate collaboration",
        "year": "2010",
        "genre": "horror",
        "views": 0,
        "episode_number": 10,
        "season_number": 1
    },
    {
        "record_id": 12,
        "type": "Serial",
        "title": "Open-architected disintermediate collaboration",
        "year": "2010",
        "genre": "horror",
        "views": 0,
        "episode_number": 11,
        "season_number": 1
    },
    {
        "record_id": 13,
        "type": "Serial",
        "title": "Open-architected disintermediate collaboration",
        "year": "2010",
        "genre": "horror",
        "views": 71,
        "episode_number": 12,
        "season_number": 1
    },
    {
        "record_id": 14,
        "type": "Serial",
        "title": "Open-architected disintermediate collaboration",
        "year": "2010",
        "genre": "horror",
        "views": 57,
        "episode_number": 13,
        "season_number": 1
    },
    {
        "record_id": 15,
        "type": "Serial",
        "title": "Open-architected disintermediate collaboration",
        "year": "2010",
        "genre": "horror",
        "views": 0,
        "episode_number": 14,
        "season_number": 1
    },
    {
        "record_id": 16,
        "type": "Serial",
        "title": "Open-architected disintermediate collaboration",
        "year": "2010",
        "genre": "horror",
        "views": 0,
        "episode_number": 15,
        "season_number": 1
    },
    {
        "record_id": 17,
        "type": "Serial",
        "title": "Open-architected disintermediate collaboration",
        "year": "2010",
        "genre": "horror",
        "views": 0,
        "episode_number": 1,
        "season_number": 2
    },
    {
        "record_id": 18,
        "type": "Serial",
        "title": "Open-architected disintermediate collaboration",
        "year": "2010",
        "genre": "horror",
        "views": 0,
        "episode_number": 2,
        "season_number": 2
    },
    {
        "record_id": 19,
        "type": "Serial",
        "title": "Open-architected disintermediate collaboration",
        "year": "2010",
        "genre": "horror",
        "views": 0,
        "episode_number": 3,
        "season_number": 2
    },
    {
        "record_id": 20,
        "type": "Serial",
        "title": "Open-architected disintermediate collaboration",
        "year": "2010",
        "genre": "horror",
        "views": 0,
        "episode_number": 4,
        "season_number": 2
    },
    {
        "record_id": 21,
        "type": "Serial",
        "title": "Open-architected disintermediate collaboration",
        "year": "2010",
        "genre": "horror",
        "views": 0,
        "episode_number": 5,
        "season_number": 2
    },
    {
        "record_id": 22,
        "type": "Serial",
        "title": "Open-architected disintermediate collaboration",
        "year": "2010",
        "genre": "horror",
        "views": 90,
        "episode_number": 6,
        "season_number": 2
    },
    {
        "record_id": 23,
        "type": "Serial",
        "title": "Open-architected disintermediate collaboration",
        "year": "2010",
        "genre": "horror",
        "views": 0,
        "episode_number": 7,
        "season_number": 2
    },
    {
        "record_id": 24,
        "type": "Serial",
        "title": "Open-architected disintermediate collaboration",
        "year": "2010",
        "genre": "horror",
        "views": 0,
        "episode_number": 8,
        "season_number": 2
    },
    {
        "record_id": 25,
        "type": "Serial",
        "title": "Open-architected disintermediate collaboration",
        "year": "2010",
        "genre": "horror",
        "views": 0,
        "episode_number": 9,
        "season_number": 2
    },
    {
        "record_id": 26,
        "type": "Serial",
        "title": "Open-architected disintermediate collaboration",
        "year": "2010",
        "genre": "horror",
        "views": 0,
        "episode_number": 10,
        "season_number": 2
    },
    {
        "record_id": 27,
        "type": "Serial",
        "title": "Open-architected disintermediate collaboration",
        "year": "2010",
        "genre": "horror",
        "views": 10,
        "episode_number": 11,
        "season_number": 2
    },
    {
        "record_id": 28,
        "type": "Serial",
        "title": "Open-architected disintermediate collaboration",
        "year": "2010",
        "genre": "horror",
        "views": 0,
        "episode_number": 12,
        "season_number": 2
    },
    {
        "record_id": 29,
        "type": "Serial",
        "title": "Open-architected disintermediate collaboration",
        "year": "2010",
        "genre": "horror",
        "views": 0,
        "episode_number": 13,
        "season_number": 2
    },
    {
        "record_id": 30,
        "type": "Serial",
        "title": "Open-architected disintermediate collaboration",
        "year": "2010",
        "genre": "horror",
        "views": 0,
        "episode_number": 14,
        "season_number": 2
    },
    {
        "record_id": 31,
        "type": "Serial",
        "title": "Open-architected disintermediate collaboration",
        "year": "2010",
        "genre": "horror",
        "views": 0,
        "episode_number": 15,
        "season_number": 2
    },
    {
        "record_id": 32,
        "type": "Serial",
        "title": "Open-architected disintermediate collaboration",
        "year": "2010",
        "genre": "horror",
        "views": 0,
        "episode_number": 1,
        "season_number": 3
    },
    {
        "record_id": 33,
        "type": "Serial",
        "title": "Open-architected disintermediate collaboration",
        "year": "2010",
        "genre": "horror",
        "views": 0,
        "episode_number": 2,
        "season_number": 3
    },
    {
        "record_id": 34,
        "type": "Serial",
        "title": "Open-architected disintermediate collaboration",
        "year": "2010",
        "genre": "horror",
        "views": 58,
        "episode_number": 3,
        "season_number": 3
    },
    {
        "record_id": 35,
        "type": "Serial",
        "title": "Open-architected disintermediate collaboration",
        "year": "2010",
        "genre": "horror",
        "views": 0,
        "episode_number": 4,
        "season_number": 3
    },
    {
        "record_id": 36,
        "type": "Serial",
        "title": "Open-architected disintermediate collaboration",
        "year": "2010",
        "genre": "horror",
        "views": 0,
        "episode_number": 5,
        "season_number": 3
    },
    {
        "record_id": 37,
        "type": "Serial",
        "title": "Open-architected disintermediate collaboration",
        "year": "2010",
        "genre": "horror",
        "views": 0,
        "episode_number": 6,
        "season_number": 3
    },
    {
        "record_id": 38,
        "type": "Serial",
        "title": "Open-architected disintermediate collaboration",
        "year": "2010",
        "genre": "horror",
        "views": 0,
        "episode_number": 7,
        "season_number": 3
    },
    {
        "record_id": 39,
        "type": "Serial",
        "title": "Open-architected disintermediate collaboration",
        "year": "2010",
        "genre": "horror",
        "views": 0,
        "episode_number": 8,
        "season_number": 3
    },
    {
        "record_id": 40,
        "type": "Serial",
        "title": "Open-architected disintermediate collaboration",
        "year": "2010",
        "genre": "horror",
        "views": 0,
        "episode_number": 9,
        "season_number": 3
    },
    {
        "record_id": 41,
        "type": "Serial",
        "title": "Open-architected disintermediate collaboration",
        "year": "2010",
        "genre": "horror",
        "views": 0,
        "episode_number": 10,
        "season_number": 3
    },
    {
        "record_id": 42,
        "type": "Serial",
        "title": "Open-architected disintermediate collaboration",
        "year": "2010",
        "genre": "horror",
        "views": 0,
        "episode_number": 11,
        "season_number": 3
    },
    {
        "record_id": 43,
        "type": "Serial",
        "title": "Open-architected disintermediate collaboration",
        "year": "2010",
        "genre": "horror",
        "views": 0,
        "episode_number": 12,
        "season_number": 3
    },
    {
        "record_id": 44,
        "type": "Serial",
        "title": "Open-architected disintermediate collaboration",
        "year": "2010",
        "genre": "horror",
        "views": 60,
        "episode_number": 13,
        "season_number": 3
    },
    {
        "record_id": 45,
        "type": "Serial",
        "title": "Open-architected disintermediate collaboration",
        "year": "2010",
        "genre": "horror",
        "views": 0,
        "episode_number": 14,
        "season_number": 3
    },
    {
        "record_id": 46,
        "type": "Serial",
        "title": "Open-architected disintermediate collaboration",
        "year": "2010",
        "genre": "horror",
        "views": 19,
        "episode_number": 15,
        "season_number": 3
    }
]